frontegg/__init__.py
frontegg/common/__init__.py
frontegg/common/async_identity_mixin.py
frontegg/common/cache/cache_manager.py
frontegg/common/cache/local_cache_manager.py
frontegg/common/cache/redis_cache_manager.py
frontegg/common/clients/__init__.py
frontegg/common/clients/async_http_client.py
frontegg/common/clients/audits_client.py
frontegg/common/clients/http_client.py
frontegg/common/clients/token_resolvers/access_token_resolver.py
frontegg/common/clients/token_resolvers/access_token_services/base_access_token_service.py
frontegg/common/clients/token_resolvers/access_token_services/cache_services/async_impl/async_cache_access_token_service.py
frontegg/common/clients/token_resolvers/access_token_services/cache_services/async_impl/async_cache_tenant_access_token_service.py
frontegg/common/clients/token_resolvers/access_token_services/cache_services/async_impl/async_cache_user_access_token_service.py
frontegg/common/clients/token_resolvers/access_token_services/cache_services/cache_access_token_service.py
frontegg/common/clients/token_resolvers/access_token_services/cache_services/cache_tenant_access_token_service.py
frontegg/common/clients/token_resolvers/access_token_services/cache_services/cache_user_access_token_service.py
frontegg/common/clients/token_resolvers/access_token_services/services/access_token_service.py
frontegg/common/clients/token_resolvers/access_token_services/services/async_impl/async_access_token_service.py
frontegg/common/clients/token_resolvers/access_token_services/services/async_impl/async_tenant_access_token_service.py
frontegg/common/clients/token_resolvers/access_token_services/services/async_impl/async_user_access_token_service.py
frontegg/common/clients/token_resolvers/access_token_services/services/tenant_access_token_service.py
frontegg/common/clients/token_resolvers/access_token_services/services/user_access_token_service.py
frontegg/common/clients/token_resolvers/async_access_token_resolver.py
frontegg-3.0.4.dist-info/LICENSE
frontegg-3.0.4.dist-info/METADATA
frontegg-3.0.4.dist-info/WHEEL
frontegg-3.0.4.dist-info/RECORD
