Metadata-Version: 2.1
Name: frontegg
Version: 3.0.4
Summary: Frontegg is a web platform where SaaS companies can set up their fully managed, scalable and brand aware - SaaS features and integrate them into their SaaS portals in up to 5 lines of code.
Home-page: https://frontegg.com/
Author: Frontegg LTD
Author-email: hello@frontegg.com
Requires-Python: >=3.8,<4.0
Classifier: Development Status :: 5 - Production/Stable
Classifier: Operating System :: OS Independent
Classifier: Programming Language :: Python
Classifier: Programming Language :: Python :: 3
Classifier: Programming Language :: Python :: 3.8
Classifier: Programming Language :: Python :: 3.9
Classifier: Programming Language :: Python :: 3.10
Classifier: Programming Language :: Python :: 3.11
Classifier: Programming Language :: Python :: 3.12
Classifier: Programming Language :: Python :: 3.13
Classifier: Programming Language :: Python :: 3.7
Classifier: Programming Language :: Python :: Implementation :: CPython
Classifier: Programming Language :: Python :: Implementation :: PyPy
Provides-Extra: fastapi
Provides-Extra: flask
Requires-Dist: PyJWT (>=2.6.0,<3.0.0)
Requires-Dist: aiohttp (>=3.6.2,<4.0.0)
Requires-Dist: arrow (>=1.2.3,<2.0.0)
Requires-Dist: cryptography (>=42.0.5)
Requires-Dist: fastapi ; extra == "fastapi"
Requires-Dist: flask (>=2.0,<3.0) ; extra == "flask"
Requires-Dist: httpx (>=0.26.0)
Requires-Dist: requests (>=2.28.2,<3.0.0)
Requires-Dist: typing-extensions (>=4.4.0,<5.0.0)
